{"idx":{"version":"2.3.3","fields":["title","contents"],"fieldVectors":[["title/components.html",[0,0.755]],["contents/components.html",[0,1.214,1,1.753,2,1.009,3,1.009,4,0.519,5,1.753,6,2.109,7,0.519,8,0.625,9,1.009,10,1.753,11,1.753,12,1.214,13,1.753,14,1.009,15,1.009,16,1.753,17,1.753,18,1.753,19,0.519,20,1.753,21,1.753,22,1.753,23,1.753]],["title/index.html",[24,0.557,25,0.967]],["contents/index.html",[]],["title/mixins.html",[26,0.755]],["contents/mixins.html",[2,0.901,3,0.901,4,0.464,7,0.464,8,0.638,19,0.464,26,1.239,27,1.565,28,1.565,29,1.565,30,2.152,31,1.968,32,1.565,33,1.565,34,1.968,35,1.968,36,1.565,37,1.565,38,1.565,39,1.565,40,1.565,41,1.968,42,1.968,43,1.968,44,1.968,45,1.968,46,1.968,47,1.565,48,1.565,49,1.565,50,1.565,51,1.565,52,1.565,53,1.565,54,0.901,55,1.565,56,1.565]],["title/undefined.html",[57,1.311]],["contents/undefined.html",[4,0.296,7,0.296,8,0.747,9,0.919,12,1.39,14,0.836,15,1.037,19,0.296,24,1.386,54,0.576,58,2.317,59,2.144,60,2.196,61,1.801,62,1.801,63,1.801,64,1.801,65,1.801,66,2.304,67,1.801,68,1.801,69,1.801,70,1.801,71,2.078,72,1.452,73,1.452,74,1.452,75,1,76,1,77,1.452,78,1.452,79,1,80,1,81,1.71,82,1,83,1.71,84,1.452,85,1.452,86,1,87,1,88,1,89,1,90,1,91,1,92,1,93,1,94,1,95,1,96,1,97,1,98,1,99,1,100,1,101,1,102,1,103,1,104,1,105,0.617,106,0.617]]],"invertedIndex":[["",{"_index":8,"title":{},"contents":{"components.html":{"position":[[79,1],[159,1]]},"mixins.html":{"position":[[207,1],[431,1],[473,1]]},"undefined.html":{"position":[[34,1],[204,2],[214,2],[254,2],[293,2],[325,2],[363,2],[397,2],[436,2],[448,1],[450,2],[453,2],[476,2],[510,2],[543,2],[569,2],[601,2],[629,2],[662,2],[665,2],[668,3],[695,1],[865,2],[880,1],[950,2],[974,1],[1077,2],[1080,2],[1215,1],[1217,2],[1315,2],[1399,2],[1509,2],[1526,2],[1566,2],[1605,2],[1637,2],[1675,2],[1709,2],[1748,2],[1760,1],[1762,2],[1765,2],[1788,2],[1822,2],[1855,2],[1881,2],[1913,2],[1941,2],[1974,2],[1977,2],[1980,3],[2007,1],[2177,2],[2192,1],[2262,2],[2286,1],[2389,2],[2392,2],[2527,1],[2529,2],[2627,2],[2711,2],[2821,2],[2833,1],[2866,1]]}}}],["0594a6",{"_index":65,"title":{},"contents":{"undefined.html":{"position":[[111,8],[316,8],[560,8],[772,8],[1628,8],[1872,8],[2084,8]]}}}],["06a6e0",{"_index":67,"title":{},"contents":{"undefined.html":{"position":[[140,8],[354,8],[592,8],[801,8],[1666,8],[1904,8],[2113,8]]}}}],["15",{"_index":104,"title":{},"contents":{"undefined.html":{"position":[[1503,5],[2815,5]]}}}],["1d4189",{"_index":61,"title":{},"contents":{"undefined.html":{"position":[[58,8],[245,8],[501,8],[719,8],[1557,8],[1813,8],[2031,8]]}}}],["224",{"_index":96,"title":{},"contents":{"undefined.html":{"position":[[1309,5],[2621,5]]}}}],["25",{"_index":85,"title":{},"contents":{"undefined.html":{"position":[[1071,5],[1484,4],[2383,5],[2796,4]]}}}],["300px",{"_index":56,"title":{},"contents":{"mixins.html":{"position":[[465,7]]}}}],["333",{"_index":76,"title":{},"contents":{"undefined.html":{"position":[[914,7],[2226,7]]}}}],["5px",{"_index":11,"title":{},"contents":{"components.html":{"position":[[96,4]]}}}],["62",{"_index":94,"title":{},"contents":{"undefined.html":{"position":[[1268,5],[2580,5]]}}}],["85",{"_index":93,"title":{},"contents":{"undefined.html":{"position":[[1263,4],[2575,4]]}}}],["95ccaa",{"_index":70,"title":{},"contents":{"undefined.html":{"position":[[195,8],[427,8],[653,8],[856,8],[1739,8],[1965,8],[2168,8]]}}}],["972d45",{"_index":69,"title":{},"contents":{"undefined.html":{"position":[[165,8],[388,8],[620,8],[826,8],[1700,8],[1932,8],[2138,8]]}}}],["add",{"_index":90,"title":{},"contents":{"undefined.html":{"position":[[1146,3],[2458,3]]}}}],["adjust",{"_index":100,"title":{},"contents":{"undefined.html":{"position":[[1407,11],[2719,11]]}}}],["aspect",{"_index":51,"title":{},"contents":{"mixins.html":{"position":[[370,6]]}}}],["author",{"_index":37,"title":{},"contents":{"mixins.html":{"position":[[170,7]]}}}],["background",{"_index":14,"title":{},"contents":{"components.html":{"position":[[115,10]]},"undefined.html":{"position":[[882,13],[1344,13],[2194,13],[2656,13]]}}}],["block",{"_index":48,"title":{},"contents":{"mixins.html":{"position":[[303,6]]}}}],["blue",{"_index":60,"title":{},"contents":{"undefined.html":{"position":[[51,6],[133,6],[239,5],[348,5],[494,6],[585,6],[712,6],[794,6],[944,5],[1551,5],[1660,5],[1806,6],[1897,6],[2024,6],[2106,6],[2256,5]]}}}],["bodytext",{"_index":79,"title":{},"contents":{"undefined.html":{"position":[[976,11],[2288,11]]}}}],["bold",{"_index":18,"title":{},"contents":{"components.html":{"position":[[153,5]]}}}],["border",{"_index":9,"title":{},"contents":{"components.html":{"position":[[81,6]]},"undefined.html":{"position":[[904,9],[1374,9],[2216,9],[2686,9],[2835,6]]}}}],["brand",{"_index":58,"title":{},"contents":{"undefined.html":{"position":[[0,6],[19,6],[680,6],[988,7],[1015,7],[1047,7],[1240,6],[1274,6],[1295,6],[1358,7],[1384,7],[1460,7],[1992,6],[2300,7],[2327,7],[2359,7],[2552,6],[2586,6],[2607,6],[2670,7],[2696,7],[2772,7],[2874,5]]}}}],["button",{"_index":6,"title":{},"contents":{"components.html":{"position":[[59,6],[71,7]]}}}],["caption",{"_index":80,"title":{},"contents":{"undefined.html":{"position":[[1004,10],[2316,10]]}}}],["class=\"button\">click",{"_index":22,"title":{},"contents":{"components.html":{"position":[[186,20]]}}}],["code",{"_index":47,"title":{},"contents":{"mixins.html":{"position":[[297,5]]}}}],["color",{"_index":12,"title":{},"contents":{"components.html":{"position":[[101,6],[126,6]]},"undefined.html":{"position":[[7,6],[26,7],[207,6],[439,8],[469,6],[672,7],[687,7],[872,7],[966,7],[1114,7],[1127,9],[1164,7],[1176,7],[1197,8],[1206,8],[1233,6],[1337,6],[1436,5],[1751,8],[1781,6],[1984,7],[1999,7],[2184,7],[2278,7],[2426,7],[2439,9],[2476,7],[2488,7],[2509,8],[2518,8],[2545,6],[2649,6],[2748,5],[2842,6]]}}}],["color(\"bord",{"_index":105,"title":{},"contents":{"undefined.html":{"position":[[2849,16]]}}}],["color__jsarc",{"_index":71,"title":{},"contents":{"undefined.html":{"position":[[217,13],[257,13],[296,13],[328,13],[366,13],[400,13],[1529,13],[1569,13],[1608,13],[1640,13],[1678,13],[1712,13]]}}}],["colors($brand",{"_index":91,"title":{},"contents":{"undefined.html":{"position":[[1150,13],[2462,13]]}}}],["colour",{"_index":106,"title":{},"contents":{"undefined.html":{"position":[[2880,7]]}}}],["compon",{"_index":0,"title":{"components.html":{"position":[[0,10]]}},"contents":{"components.html":{"position":[[0,11],[30,10]]}}}],["configur",{"_index":28,"title":{},"contents":{"mixins.html":{"position":[[30,12]]}}}],["contain",{"_index":31,"title":{},"contents":{"mixins.html":{"position":[[70,11],[421,9]]}}}],["container(400px",{"_index":55,"title":{},"contents":{"mixins.html":{"position":[[448,16]]}}}],["css",{"_index":46,"title":{},"contents":{"mixins.html":{"position":[[284,4],[310,3]]}}}],["custom",{"_index":27,"title":{},"contents":{"mixins.html":{"position":[[8,6]]}}}],["d8262e",{"_index":63,"title":{},"contents":{"undefined.html":{"position":[[88,8],[284,8],[534,8],[749,8],[1596,8],[1846,8],[2061,8]]}}}],["dark",{"_index":81,"title":{},"contents":{"undefined.html":{"position":[[1023,6],[1302,6],[1392,6],[2335,6],[2614,6],[2704,6]]}}}],["ddf",{"_index":95,"title":{},"contents":{"undefined.html":{"position":[[1289,5],[2601,5]]}}}],["desatur",{"_index":103,"title":{},"contents":{"undefined.html":{"position":[[1489,13],[2801,13]]}}}],["document",{"_index":25,"title":{"index.html":{"position":[[6,13]]}},"contents":{}}],["drop",{"_index":33,"title":{},"contents":{"mixins.html":{"position":[[98,4]]}}}],["element’",{"_index":44,"title":{},"contents":{"mixins.html":{"position":[[233,9],[267,9]]}}}],["emb",{"_index":30,"title":{},"contents":{"mixins.html":{"position":[[64,5],[414,6],[442,5]]}}}],["everyth",{"_index":87,"title":{},"contents":{"undefined.html":{"position":[[1089,10],[2401,10]]}}}],["exampl",{"_index":19,"title":{},"contents":{"components.html":{"position":[[161,7]]},"mixins.html":{"position":[[401,7]]},"undefined.html":{"position":[[1512,8],[2824,8]]}}}],["exist",{"_index":98,"title":{},"contents":{"undefined.html":{"position":[[1328,8],[2640,8]]}}}],["explicit",{"_index":73,"title":{},"contents":{"undefined.html":{"position":[[460,8],[1224,8],[1772,8],[2536,8]]}}}],["fff",{"_index":75,"title":{},"contents":{"undefined.html":{"position":[[896,7],[2208,7]]}}}],["font",{"_index":16,"title":{},"contents":{"components.html":{"position":[[140,4]]}}}],["function",{"_index":102,"title":{},"contents":{"undefined.html":{"position":[[1442,9],[2754,9]]}}}],["gener",{"_index":57,"title":{"undefined.html":{"position":[[0,7]]}},"contents":{}}],["green",{"_index":15,"title":{},"contents":{"components.html":{"position":[[133,6]]},"undefined.html":{"position":[[187,7],[420,6],[645,7],[848,7],[1732,6],[1957,7],[2160,7]]}}}],["height",{"_index":45,"title":{},"contents":{"mixins.html":{"position":[[249,8],[277,6]]}}}],["helper",{"_index":32,"title":{},"contents":{"mixins.html":{"position":[[82,6]]}}}],["href",{"_index":21,"title":{},"contents":{"components.html":{"position":[[177,8]]}}}],["hsl(330",{"_index":92,"title":{},"contents":{"undefined.html":{"position":[[1254,8],[2566,8]]}}}],["html",{"_index":20,"title":{},"contents":{"components.html":{"position":[[169,4]]}}}],["ifram",{"_index":35,"title":{},"contents":{"mixins.html":{"position":[[125,6],[344,6]]}}}],["includ",{"_index":54,"title":{},"contents":{"mixins.html":{"position":[[433,8]]},"undefined.html":{"position":[[1137,8],[2449,8]]}}}],["inner",{"_index":49,"title":{},"contents":{"mixins.html":{"position":[[338,5]]}}}],["jsarc",{"_index":24,"title":{"index.html":{"position":[[0,5]]}},"contents":{"undefined.html":{"position":[[36,6],[67,6],[97,6],[120,6],[149,6],[174,6],[479,6],[513,6],[546,6],[572,6],[604,6],[632,6],[697,6],[728,6],[758,6],[781,6],[810,6],[835,6],[930,7],[1791,6],[1825,6],[1858,6],[1884,6],[1916,6],[1944,6],[2009,6],[2040,6],[2070,6],[2093,6],[2122,6],[2147,6],[2242,7],[2868,5]]}}}],["length",{"_index":43,"title":{},"contents":{"mixins.html":{"position":[[224,8],[258,8]]}}}],["light",{"_index":66,"title":{},"contents":{"undefined.html":{"position":[[127,5],[181,5],[342,5],[414,5],[579,5],[639,5],[788,5],[842,5],[938,5],[996,7],[1281,7],[1366,7],[1654,5],[1726,5],[1891,5],[1951,5],[2100,5],[2154,5],[2250,5],[2308,7],[2593,7],[2678,7]]}}}],["link",{"_index":77,"title":{},"contents":{"undefined.html":{"position":[[922,7],[1452,7],[2234,7],[2764,7]]}}}],["magazin",{"_index":39,"title":{},"contents":{"mixins.html":{"position":[[187,8]]}}}],["main",{"_index":88,"title":{},"contents":{"undefined.html":{"position":[[1109,4],[2421,4]]}}}],["maintain",{"_index":50,"title":{},"contents":{"mixins.html":{"position":[[356,9]]}}}],["make",{"_index":99,"title":{},"contents":{"undefined.html":{"position":[[1402,4],[2714,4]]}}}],["map",{"_index":89,"title":{},"contents":{"undefined.html":{"position":[[1122,4],[2434,4]]}}}],["me</a",{"_index":23,"title":{},"contents":{"components.html":{"position":[[207,6]]}}}],["merg",{"_index":86,"title":{},"contents":{"undefined.html":{"position":[[1083,5],[2395,5]]}}}],["mixin",{"_index":26,"title":{"mixins.html":{"position":[[0,6]]}},"contents":{"mixins.html":{"position":[[0,7],[57,6],[89,5]]}}}],["need",{"_index":101,"title":{},"contents":{"undefined.html":{"position":[[1422,7],[2734,7]]}}}],["output",{"_index":41,"title":{},"contents":{"mixins.html":{"position":[[209,6],[289,7]]}}}],["paramet",{"_index":40,"title":{},"contents":{"mixins.html":{"position":[[196,10]]}}}],["pink",{"_index":83,"title":{},"contents":{"undefined.html":{"position":[[1055,5],[1247,6],[1468,5],[2367,5],[2559,6],[2780,5]]}}}],["primari",{"_index":59,"title":{},"contents":{"undefined.html":{"position":[[43,7],[74,7],[231,7],[271,7],[486,7],[520,7],[704,7],[735,7],[1543,7],[1583,7],[1798,7],[1832,7],[2016,7],[2047,7]]}}}],["purpl",{"_index":68,"title":{},"contents":{"undefined.html":{"position":[[156,8],[380,7],[611,8],[817,8],[1692,7],[1923,8],[2129,8]]}}}],["radiu",{"_index":10,"title":{},"contents":{"components.html":{"position":[[88,7]]}}}],["ratio",{"_index":52,"title":{},"contents":{"mixins.html":{"position":[[377,5]]}}}],["re",{"_index":2,"title":{},"contents":{"components.html":{"position":[[19,2]]},"mixins.html":{"position":[[15,2]]}}}],["red",{"_index":62,"title":{},"contents":{"undefined.html":{"position":[[82,5],[279,4],[528,5],[743,5],[1591,4],[1840,5],[2055,5]]}}}],["refer",{"_index":97,"title":{},"contents":{"undefined.html":{"position":[[1318,9],[2630,9]]}}}],["resiz",{"_index":53,"title":{},"contents":{"mixins.html":{"position":[[392,8]]}}}],["respons",{"_index":36,"title":{},"contents":{"mixins.html":{"position":[[158,11]]}}}],["scss",{"_index":7,"title":{},"contents":{"components.html":{"position":[[66,4]]},"mixins.html":{"position":[[409,4]]},"undefined.html":{"position":[[14,4],[1521,4]]}}}],["secondarytext",{"_index":82,"title":{},"contents":{"undefined.html":{"position":[[1030,16],[2342,16]]}}}],["set",{"_index":72,"title":{},"contents":{"undefined.html":{"position":[[456,3],[1220,3],[1768,3],[2532,3]]}}}],["shade",{"_index":84,"title":{},"contents":{"undefined.html":{"position":[[1061,9],[1474,9],[2373,9],[2786,9]]}}}],["site",{"_index":5,"title":{},"contents":{"components.html":{"position":[[53,5]]}}}],["small",{"_index":1,"title":{},"contents":{"components.html":{"position":[[12,6]]}}}],["smash",{"_index":38,"title":{},"contents":{"mixins.html":{"position":[[178,8]]}}}],["teal",{"_index":64,"title":{},"contents":{"undefined.html":{"position":[[104,6],[310,5],[553,6],[765,6],[1622,5],[1865,6],[2077,6]]}}}],["tool",{"_index":29,"title":{},"contents":{"mixins.html":{"position":[[43,5]]}}}],["typograph",{"_index":78,"title":{},"contents":{"undefined.html":{"position":[[953,12],[1184,12],[2265,12],[2496,12]]}}}],["ui",{"_index":74,"title":{},"contents":{"undefined.html":{"position":[[868,3],[1172,3],[2180,3],[2484,3]]}}}],["us",{"_index":4,"title":{},"contents":{"components.html":{"position":[[41,4]]},"mixins.html":{"position":[[52,4]]},"undefined.html":{"position":[[1430,5],[2742,5]]}}}],["useabl",{"_index":3,"title":{},"contents":{"components.html":{"position":[[22,7]]},"mixins.html":{"position":[[18,7]]}}}],["weight",{"_index":17,"title":{},"contents":{"components.html":{"position":[[145,7]]}}}],["white",{"_index":13,"title":{},"contents":{"components.html":{"position":[[108,6]]}}}],["width",{"_index":42,"title":{},"contents":{"mixins.html":{"position":[[216,7],[243,5]]}}}],["wrapper",{"_index":34,"title":{},"contents":{"mixins.html":{"position":[[110,7],[322,7]]}}}]],"pipeline":["stemmer"]},"store":{"components.html":{"filename":"components.html","title":"components","contents":"Components: small, re-useable components used on the site. Button scss .button { border-radius: 5px; color: white; background-color: green; font-weight: bold; } Example html <a href=\"#\" class=\"button\">Click me</a>"},"index.html":{"filename":"index.html","title":"jsarc Documentation","contents":""},"mixins.html":{"filename":"mixins.html","title":"mixins","contents":"Mixins: custom re-useable but configurable tools we use. @mixin embed-container() Helper mixin to drop on the wrapper for an iframe that you would like to be responsive. Author: Smashing Magazine Parameters & Output $width: (Length) Element’s width $height: (Length) Element’s height {CSS output} (code block) CSS for the wrapper and the inner iframe that maintains the aspect ratio as it is resized. Example scss .embed-container { @include embed-container(400px, 300px); }"},"undefined.html":{"filename":"undefined.html","title":"General","contents":"$brand-colors scss $brand-colors: ( \"jsarc-primary-blue\": #1d4189, \"jsarc-primary-red\": #d8262e, \"jsarc-teal\": #0594a6, \"jsarc-light-blue\": #06a6e0, \"jsarc-purple\": #972d45, \"jsarc-light-green\": #95ccaa, ); colors // $color__jsarc-primary-blue: #1d4189; // $color__jsarc-primary-red: #d8262e; // $color__jsarc-teal: #0594a6; // $color__jsarc-light-blue: #06a6e0; // $color__jsarc-purple: #972d45; // $color__jsarc-light-green: #95ccaa; // $colors: ( // // set explicit colors // \"jsarc-primary-blue\": #1d4189, // \"jsarc-primary-red\": #d8262e, // \"jsarc-teal\": #0594a6, // \"jsarc-light-blue\": #06a6e0, // \"jsarc-purple\": #972d45, // \"jsarc-light-green\": #95ccaa, // ); /// @colors $brand-colors: ( \"jsarc-primary-blue\": #1d4189, \"jsarc-primary-red\": #d8262e, \"jsarc-teal\": #0594a6, \"jsarc-light-blue\": #06a6e0, \"jsarc-purple\": #972d45, \"jsarc-light-green\": #95ccaa, ); $ui-colors: ( \"background\": \"#fff\", \"border\": \"#333\", \"link\": \"#jsarc-light-blue\" ); $typographic-colors: ( \"bodyText\": \"#brand-light\", \"caption\": \"#brand-dark\", \"secondaryText\": \"#brand-pink\" (\"shade\": 25%), ); // merge everything into the main $colors map… ///colors @include add-colors($brand-colors, $ui-colors, $typographic-colors); $colors: ( // set explicit colors \"brand-pink\": hsl(330, 85%, 62%), \"brand-light\": #ddf, \"brand-dark\": #224, // reference existing colors \"background\": \"#brand-light\", \"border\": \"#brand-dark\", // make adjustments as needed, using color functions \"link\": \"#brand-pink\" (\"shade\": 25%, \"desaturate\": 15%), ); .example scss // $color__jsarc-primary-blue: #1d4189; // $color__jsarc-primary-red: #d8262e; // $color__jsarc-teal: #0594a6; // $color__jsarc-light-blue: #06a6e0; // $color__jsarc-purple: #972d45; // $color__jsarc-light-green: #95ccaa; // $colors: ( // // set explicit colors // \"jsarc-primary-blue\": #1d4189, // \"jsarc-primary-red\": #d8262e, // \"jsarc-teal\": #0594a6, // \"jsarc-light-blue\": #06a6e0, // \"jsarc-purple\": #972d45, // \"jsarc-light-green\": #95ccaa, // ); /// @colors $brand-colors: ( \"jsarc-primary-blue\": #1d4189, \"jsarc-primary-red\": #d8262e, \"jsarc-teal\": #0594a6, \"jsarc-light-blue\": #06a6e0, \"jsarc-purple\": #972d45, \"jsarc-light-green\": #95ccaa, ); $ui-colors: ( \"background\": \"#fff\", \"border\": \"#333\", \"link\": \"#jsarc-light-blue\" ); $typographic-colors: ( \"bodyText\": \"#brand-light\", \"caption\": \"#brand-dark\", \"secondaryText\": \"#brand-pink\" (\"shade\": 25%), ); // merge everything into the main $colors map… ///colors @include add-colors($brand-colors, $ui-colors, $typographic-colors); $colors: ( // set explicit colors \"brand-pink\": hsl(330, 85%, 62%), \"brand-light\": #ddf, \"brand-dark\": #224, // reference existing colors \"background\": \"#brand-light\", \"border\": \"#brand-dark\", // make adjustments as needed, using color functions \"link\": \"#brand-pink\" (\"shade\": 25%, \"desaturate\": 15%), ); .example { border-color: color(\"border\"); } JSaRC Brand Colours"}}}